colorfulpanda/__init__.py
colorfulpanda/index.py
colorfulpanda/Style/Base.py
colorfulpanda/Style/GreenToCyan.py
colorfulpanda/Style/Red.py
colorfulpanda/Style/__init__.py
colorfulpanda/mov/BlinkBlock.py
colorfulpanda/mov/PanicWhiteRed.py
colorfulpanda/mov/Skull.py
colorfulpanda/mov/__init__.py
colorfulpanda/utils/__init__.py
colorfulpanda/utils/color.py
colorfulpanda/utils/main.py
colorfulpanda/utils/ASCIIPicMaker/__init__.py
colorfulpanda/utils/ASCIIPicMaker/main.py
src/__init__.py
src/index.py
src/Style/Base.py
src/Style/GreenToCyan.py
src/Style/Red.py
src/Style/__init__.py
src/mov/BlinkBlock.py
src/mov/Skull.py
src/mov/__init__.py
src/utils/__init__.py
src/utils/color.py
src/utils/main.py
src/utils/ASCIIPicMaker/__init__.py
src/utils/ASCIIPicMaker/main.py
colorfulpanda-0.4.dist-info/METADATA
colorfulpanda-0.4.dist-info/WHEEL
colorfulpanda-0.4.dist-info/top_level.txt
colorfulpanda-0.4.dist-info/RECORD
