Metadata-Version: 2.1
Name: colorfulpanda
Version: 0.4
Summary: a colorful printer
Home-page: https://github.com/PandaTea/colorfulPanda
Author: LeePanda
Author-email: leepandapia@gmail.com
License: UNKNOWN
Platform: UNKNOWN
Classifier: Programming Language :: Python :: 3
Classifier: License :: OSI Approved :: MIT License
Classifier: Operating System :: OS Independent
Requires-Dist: sty
Requires-Dist: tqdm
